drcomp/__init__.py
drcomp-0.0.1a0.dist-info/LICENSE
drcomp-0.0.1a0.dist-info/WHEEL
drcomp-0.0.1a0.dist-info/METADATA
drcomp-0.0.1a0.dist-info/RECORD
