Metadata-Version: 2.1
Name: drcomp
Version: 0.0.1a0
Summary: Dimensionality Reduction Comparison
Home-page: https://github.com/MoritzM00/drcomp
License: MIT
Author: Moritz Mistol
Author-email: moritz.mistol@gmail.com
Requires-Python: >=3.8,<3.12
Classifier: Development Status :: 1 - Planning
Classifier: License :: OSI Approved :: MIT License
Classifier: Programming Language :: Python :: 3
Classifier: Programming Language :: Python :: 3.8
Classifier: Programming Language :: Python :: 3.9
Classifier: Programming Language :: Python :: 3.10
Requires-Dist: numpy (>=1.23.2)
Requires-Dist: scikit-learn (>=1.1.2)
Project-URL: Changelog, https://github.com/MoritzM00/drcomp/releases
Project-URL: Documentation, https://drcomp.readthedocs.io
Project-URL: Repository, https://github.com/MoritzM00/drcomp
